certbot_dns_innovativity/__init__.py
certbot_dns_innovativity/dns_innovativity.py
certbot_dns_innovativity-1.0.1.dist-info/LICENSE.txt
certbot_dns_innovativity-1.0.1.dist-info/METADATA
certbot_dns_innovativity-1.0.1.dist-info/WHEEL
certbot_dns_innovativity-1.0.1.dist-info/entry_points.txt
certbot_dns_innovativity-1.0.1.dist-info/top_level.txt
certbot_dns_innovativity-1.0.1.dist-info/RECORD
